csvpp/__init__.py
csvpp/csvpp.py
csvpp-0.1.0.data/scripts/csvpp
csvpp-0.1.0.dist-info/DESCRIPTION.rst
csvpp-0.1.0.dist-info/METADATA
csvpp-0.1.0.dist-info/metadata.json
csvpp-0.1.0.dist-info/RECORD
csvpp-0.1.0.dist-info/top_level.txt
csvpp-0.1.0.dist-info/WHEEL
