Metadata-Version: 2.0
Name: csvpp
Version: 0.1.0
Summary: CSV reformatter to align columns
Home-page: https://github.com/johanlu/csvpp
Author: Johan Lübcke
Author-email: johan@lubcke.se
License: MIT
Keywords: csvpp
Platform: UNKNOWN
Classifier: Development Status :: 2 - Pre-Alpha
Classifier: Intended Audience :: Developers
Classifier: License :: OSI Approved :: MIT License
Classifier: Natural Language :: English
Classifier: Programming Language :: Python :: 2
Classifier: Programming Language :: Python :: 2.6
Classifier: Programming Language :: Python :: 2.7
Classifier: Programming Language :: Python :: 3
Classifier: Programming Language :: Python :: 3.3
Classifier: Programming Language :: Python :: Implementation :: PyPy
